PirxcyPackage/__init__.py
PirxcyAdmin-1.0.dist-info/METADATA
PirxcyAdmin-1.0.dist-info/WHEEL
PirxcyAdmin-1.0.dist-info/top_level.txt
PirxcyAdmin-1.0.dist-info/RECORD
