Metadata-Version: 2.1
Name: PirxcyAdmin
Version: 1.0
Summary: PirxcyBot in a PyPi package form to easily be ran on repl. Or in a simple py file
Home-page: https://github.com/PirxcyFinal/PirxcyBot.git
Author: Pirxcy
License: UNKNOWN
Platform: UNKNOWN
Classifier: Programming Language :: Python :: 3
Classifier: License :: OSI Approved :: MIT License
Classifier: Operating System :: OS Independent
Requires-Dist: crayons
Requires-Dist: random
Requires-Dist: os
Requires-Dist: sys
Requires-Dist: functools
Requires-Dist: json
Requires-Dist: datetime
Requires-Dist: httptools
Requires-Dist: fortnitepy
Requires-Dist: psutil
Requires-Dist: pypresence
Requires-Dist: BenBotAsync
Requires-Dist: FortniteAPIAsync
Requires-Dist: uvloop
Requires-Dist: sanic
Requires-Dist: aiohttp
